{
    "DateLastVerified": "2023-05-08T04:07:00Z",
    "ID": 261769,
    "UUID": "A36A8FD3-3563-4B1D-A673-1B88F04C3945",
    "DataProviderID": 19,
    "DataProvidersReference": "14500",
    "AddressInfo": {
        "ID": 262153,
        "Title": "Trumslagarvägen 21",
        "AddressLine1": "Trumslagarvägen 21",
        "Town": "GÄVLE",
        "StateOrProvince": "GÄVLEBORG",
        "Postcode": "80432",
        "CountryID": 216,
        "Latitude": 60.664637,
        "Longitude": 17.236582,
        "AccessComments": "",
        "DistanceUnit": 0
    },
    "Connections": [
        {
            "ID": 443979,
            "ConnectionTypeID": 25,
            "Reference": "1",
            "LevelID": 2,
            "Amps": 16,
            "Voltage": 400,
            "PowerKW": 11,
            "CurrentTypeID": 20,
            "Comments": "Mode 3"
        },
        {
            "ID": 443980,
            "ConnectionTypeID": 25,
            "Reference": "2",
            "LevelID": 2,
            "Amps": 16,
            "Voltage": 400,
            "PowerKW": 11,
            "CurrentTypeID": 20,
            "Comments": "Mode 3"
        }
    ],
    "NumberOfPoints": 2,
    "DateLastStatusUpdate": "2023-05-08T04:07:00Z",
    "DateCreated": "2023-05-01T04:24:00Z",
    "SubmissionStatusTypeID": 100
}