{
    "DateLastVerified": "2018-07-23T13:11:00Z",
    "ID": 77762,
    "UUID": "5CA1B712-7674-46D7-93B0-DC385B615D84",
    "DataProviderID": 1,
    "OperatorID": 3259,
    "OperatorsReference": "SKZSEET513712UIJE001*1",
    "UsageTypeID": 1,
    "AddressInfo": {
        "ID": 78108,
        "Title": "Dvory",
        "AddressLine1": "Dvory 4",
        "Town": "Bratislava",
        "Postcode": "851 01",
        "CountryID": 204,
        "Latitude": 48.12521,
        "Longitude": 17.10548,
        "DistanceUnit": 0
    },
    "Connections": [
        {
            "ID": 112344,
            "ConnectionTypeID": 2,
            "StatusTypeID": 50,
            "LevelID": 3,
            "PowerKW": 50,
            "CurrentTypeID": 30,
            "Quantity": 1
        }
    ],
    "NumberOfPoints": 1,
    "StatusTypeID": 100,
    "DateLastStatusUpdate": "2018-07-23T13:11:00Z",
    "DateCreated": "2017-01-23T15:48:00Z",
    "SubmissionStatusTypeID": 200
}