{
    "DateLastVerified": "2023-12-03T09:59:00Z",
    "ID": 280797,
    "UUID": "A1A4E01E-364B-4996-9EB4-776261232945",
    "DataProviderID": 1,
    "OperatorID": 3328,
    "UsageTypeID": 4,
    "AddressInfo": {
        "ID": 281184,
        "Title": "Centro polifunzionale",
        "AddressLine1": "Via Morgioni",
        "Town": "Ischia ",
        "StateOrProvince": "NA",
        "Postcode": "80077",
        "CountryID": 112,
        "Latitude": 40.7354787519902,
        "Longitude": 13.941229459156716,
        "DistanceUnit": 0
    },
    "Connections": [
        {
            "ID": 488476,
            "ConnectionTypeID": 25,
            "StatusTypeID": 50,
            "LevelID": 2,
            "PowerKW": 22,
            "CurrentTypeID": 20,
            "Quantity": 2
        }
    ],
    "NumberOfPoints": 1,
    "StatusTypeID": 50,
    "DateLastStatusUpdate": "2023-12-03T09:59:00Z",
    "DateCreated": "2023-11-30T09:58:00Z",
    "SubmissionStatusTypeID": 200
}