{
    "DateLastVerified": "2023-12-02T09:29:00Z",
    "ID": 280703,
    "UUID": "16C4DC96-4B80-4344-BA21-BE3034F06B20",
    "DataProviderID": 1,
    "OperatorID": 3328,
    "UsageTypeID": 4,
    "UsageCost": "0.50 €/kWh",
    "AddressInfo": {
        "ID": 281090,
        "Title": "Elettrica Led",
        "AddressLine1": "Via Papa Giovanni XXIII",
        "Town": "Uboldo",
        "StateOrProvince": "Varese",
        "Postcode": "21040",
        "CountryID": 112,
        "Latitude": 45.6025733473642,
        "Longitude": 8.9999773822002,
        "DistanceUnit": 0
    },
    "Connections": [
        {
            "ID": 488231,
            "ConnectionTypeID": 25,
            "StatusTypeID": 50,
            "LevelID": 2,
            "PowerKW": 22,
            "CurrentTypeID": 20,
            "Quantity": 4
        }
    ],
    "NumberOfPoints": 1,
    "StatusTypeID": 50,
    "DateLastStatusUpdate": "2023-12-02T09:29:00Z",
    "DateCreated": "2023-11-29T09:27:00Z",
    "SubmissionStatusTypeID": 200
}