{
    "DateLastVerified": "2025-06-24T07:47:00Z",
    "ID": 56610,
    "UUID": "0107D3CB-F2E7-43E8-9A40-C793AB533576",
    "DataProviderID": 2,
    "DataProvidersReference": "70665",
    "UsageTypeID": 1,
    "AddressInfo": {
        "ID": 56956,
        "Title": "City of Niles - District Library",
        "AddressLine1": "620 E Main St",
        "Town": "Niles",
        "StateOrProvince": "MI",
        "Postcode": "49120",
        "CountryID": 2,
        "Latitude": 41.829209,
        "Longitude": -86.25175,
        "ContactTelephone1": "269-683-0075",
        "AccessComments": "24 hours daily",
        "RelatedURL": "",
        "DistanceUnit": 0
    },
    "Connections": [
        {
            "ID": 71370,
            "ConnectionTypeID": 1,
            "LevelID": 2,
            "Amps": 16,
            "Voltage": 230,
            "PowerKW": 3.7,
            "CurrentTypeID": 10,
            "Quantity": 1,
            "Comments": "kW power is an estimate based on the connection type"
        }
    ],
    "StatusTypeID": 50,
    "DateLastStatusUpdate": "2025-06-24T07:47:00Z",
    "DateCreated": "2015-11-04T08:42:00Z",
    "SubmissionStatusTypeID": 100
}