{
    "DateLastVerified": "2024-02-20T10:43:00Z",
    "ID": 116068,
    "UUID": "2F307952-8F74-4467-AA1C-FDFE517C8C46",
    "DataProviderID": 2,
    "DataProvidersReference": "114444",
    "OperatorID": 23,
    "UsageTypeID": 1,
    "AddressInfo": {
        "ID": 116414,
        "Title": "250 Main Hotel - Tesla Destination",
        "AddressLine1": "250 Main St",
        "Town": "Rockland",
        "StateOrProvince": "ME",
        "Postcode": "04841",
        "CountryID": 2,
        "Latitude": 44.10102,
        "Longitude": -69.109375,
        "ContactTelephone1": "207-594-5994  877-798-3752",
        "AccessComments": "",
        "RelatedURL": "https://www.tesla.com/destination-charging",
        "DistanceUnit": 0
    },
    "Connections": [
        {
            "ID": 163128,
            "ConnectionTypeID": 30,
            "LevelID": 2,
            "Amps": 16,
            "Voltage": 230,
            "PowerKW": 3.7,
            "CurrentTypeID": 10,
            "Quantity": 2,
            "Comments": "kW power is an estimate based on the connection type"
        }
    ],
    "StatusTypeID": 50,
    "DateLastStatusUpdate": "2024-02-20T10:43:00Z",
    "DateCreated": "2019-02-11T07:13:00Z",
    "SubmissionStatusTypeID": 100
}