{
    "DateLastVerified": "2018-10-12T05:31:00Z",
    "ID": 107187,
    "UUID": "539F1D81-5332-48AA-A5E1-CE530AD28F51",
    "DataProviderID": 1,
    "OperatorID": 23,
    "OperatorsReference": "28555",
    "UsageTypeID": 1,
    "UsageCost": "$0.23/kWh; other tariffs for older cars",
    "AddressInfo": {
        "ID": 107533,
        "Title": "Mansfield Crossing",
        "AddressLine1": " 280 School Street ",
        "Town": "Mansfield, ",
        "StateOrProvince": "MA",
        "Postcode": "02048",
        "CountryID": 2,
        "Latitude": 42.0134730135724,
        "Longitude": -71.2313405982865,
        "DistanceUnit": 0
    },
    "Connections": [
        {
            "ID": 151165,
            "ConnectionTypeID": 27,
            "StatusTypeID": 50,
            "LevelID": 3,
            "PowerKW": 120,
            "CurrentTypeID": 30,
            "Quantity": 8
        }
    ],
    "NumberOfPoints": 8,
    "StatusTypeID": 50,
    "DateLastStatusUpdate": "2018-10-12T05:31:00Z",
    "DateCreated": "2018-07-22T13:02:00Z",
    "SubmissionStatusTypeID": 200
}