{
    "DateLastVerified": "2023-07-12T07:53:00Z",
    "ID": 138209,
    "UUID": "80F30C51-A95F-4C91-B85D-88E5FFDAC93F",
    "DataProviderID": 2,
    "DataProvidersReference": "148982",
    "OperatorID": 39,
    "UsageTypeID": 1,
    "AddressInfo": {
        "ID": 138558,
        "Title": "Shops 13",
        "AddressLine1": "815 13th Street NE",
        "Town": "Fort Lauderdale",
        "StateOrProvince": "FL",
        "Postcode": "33305",
        "CountryID": 2,
        "Latitude": 26.142584,
        "Longitude": -80.135133,
        "ContactTelephone1": "800-663-5633",
        "AccessComments": "24 hours daily",
        "RelatedURL": "https://semaconnect.com/",
        "DistanceUnit": 0
    },
    "Connections": [
        {
            "ID": 193274,
            "ConnectionTypeID": 1,
            "LevelID": 2,
            "Amps": 16,
            "Voltage": 230,
            "PowerKW": 3.7,
            "CurrentTypeID": 10,
            "Quantity": 1,
            "Comments": "kW power is an estimate based on the connection type"
        }
    ],
    "StatusTypeID": 50,
    "DateLastStatusUpdate": "2023-07-12T07:53:00Z",
    "DateCreated": "2019-12-24T09:08:00Z",
    "SubmissionStatusTypeID": 100
}