{
    "DateLastVerified": "2024-03-04T13:25:00Z",
    "ID": 232219,
    "UUID": "B5E78E16-764C-4857-B47C-972120A07681",
    "DataProviderID": 1,
    "OperatorID": 15,
    "UsageTypeID": 1,
    "AddressInfo": {
        "ID": 232602,
        "Title": "Target Roseville",
        "AddressLine1": "1515 County Road B W",
        "Town": "Roseville",
        "StateOrProvince": "MN",
        "Postcode": "55113",
        "CountryID": 2,
        "Latitude": 45.006605,
        "Longitude": -93.163554,
        "ContactTelephone1": "877-455-3833",
        "AccessComments": "24 hours daily",
        "RelatedURL": "https://www.evgo.com/",
        "DistanceUnit": 0
    },
    "Connections": [
        {
            "ID": 384038,
            "ConnectionTypeID": 2,
            "StatusTypeID": 50,
            "LevelID": 3,
            "PowerKW": 100,
            "CurrentTypeID": 30,
            "Quantity": 2,
            "Comments": ""
        },
        {
            "ID": 384039,
            "ConnectionTypeID": 32,
            "StatusTypeID": 50,
            "LevelID": 3,
            "PowerKW": 350,
            "CurrentTypeID": 30,
            "Quantity": 4,
            "Comments": ""
        },
        {
            "ID": 527977,
            "ConnectionTypeID": 32,
            "StatusTypeID": 50,
            "LevelID": 3,
            "PowerKW": 100,
            "CurrentTypeID": 30,
            "Quantity": 2
        }
    ],
    "StatusTypeID": 50,
    "DateLastStatusUpdate": "2024-03-04T13:25:00Z",
    "DateCreated": "2023-02-13T05:33:00Z",
    "SubmissionStatusTypeID": 100
}