{
    "IsRecentlyVerified": false,
    "ID": 159258,
    "UUID": "AAEEDDBD-B387-4F9A-ABC6-8B82659A1064",
    "DataProviderID": 2,
    "DataProvidersReference": "152873",
    "OperatorID": 3293,
    "UsageTypeID": 1,
    "AddressInfo": {
        "ID": 159615,
        "Title": "Hamilton Marketplace",
        "AddressLine1": "5800 Nave Ct",
        "Town": "Novato",
        "StateOrProvince": "CA",
        "Postcode": "94947",
        "CountryID": 2,
        "Latitude": 38.063395,
        "Longitude": -122.533758,
        "ContactTelephone1": "888-264-2208",
        "AccessComments": "6am-12pm daily",
        "RelatedURL": "https://voltacharging.com/",
        "DistanceUnit": 0
    },
    "Connections": [
        {
            "ID": 229392,
            "ConnectionTypeID": 1,
            "LevelID": 2,
            "Amps": 16,
            "Voltage": 230,
            "PowerKW": 3.7,
            "CurrentTypeID": 10,
            "Quantity": 2
        }
    ],
    "StatusTypeID": 50,
    "DateLastStatusUpdate": "2020-06-26T02:59:00Z",
    "DataQualityLevel": 3,
    "DateCreated": "2020-06-26T02:59:00Z",
    "SubmissionStatusTypeID": 100
}