{
    "DateLastVerified": "2019-12-24T09:05:00Z",
    "ID": 137582,
    "UUID": "40BEAAC4-0C43-41E6-8C54-48A2A7645A20",
    "DataProviderID": 2,
    "DataProvidersReference": "116891",
    "OperatorID": 5,
    "UsageTypeID": 1,
    "AddressInfo": {
        "ID": 137928,
        "Title": "CARCHARGING",
        "AddressLine1": "1821 Farm to Market 685",
        "Town": "Pflugerville",
        "StateOrProvince": "TX",
        "Postcode": "78660",
        "CountryID": 2,
        "Latitude": 30.4549274,
        "Longitude": -97.6021957,
        "ContactTelephone1": "888-758-4389",
        "AccessComments": "24 hours daily",
        "RelatedURL": "http://www.chargepoint.com/",
        "DistanceUnit": 0
    },
    "Connections": [
        {
            "ID": 192521,
            "ConnectionTypeID": 1,
            "LevelID": 2,
            "Amps": 16,
            "Voltage": 230,
            "PowerKW": 3,
            "CurrentTypeID": 10,
            "Quantity": 2
        }
    ],
    "StatusTypeID": 50,
    "DateLastStatusUpdate": "2019-12-24T09:05:00Z",
    "DateCreated": "2019-12-24T09:05:00Z",
    "SubmissionStatusTypeID": 100
}