{
    "DateLastVerified": "2025-06-24T08:20:00Z",
    "ID": 283749,
    "UUID": "C2A0DDBE-08FB-4A05-9D06-C45422A40AD6",
    "DataProviderID": 2,
    "DataProvidersReference": "320952",
    "OperatorID": 3865,
    "UsageTypeID": 2,
    "AddressInfo": {
        "ID": 284136,
        "Title": "Avis Juneau (Downtown)",
        "AddressLine1": "111 Mill St",
        "Town": "Juneau",
        "StateOrProvince": "AK",
        "Postcode": "99801",
        "CountryID": 2,
        "Latitude": 58.28745,
        "Longitude": -134.38595,
        "ContactTelephone1": "",
        "AccessComments": "24 hours daily",
        "RelatedURL": "https://turnongreen.com",
        "DistanceUnit": 0
    },
    "Connections": [
        {
            "ID": 491879,
            "ConnectionTypeID": 1,
            "LevelID": 2,
            "Amps": 16,
            "Voltage": 230,
            "PowerKW": 3.7,
            "CurrentTypeID": 10,
            "Quantity": 2,
            "Comments": "kW power is an estimate based on the connection type"
        }
    ],
    "StatusTypeID": 50,
    "DateLastStatusUpdate": "2025-06-24T08:20:00Z",
    "DateCreated": "2023-12-04T04:38:00Z",
    "SubmissionStatusTypeID": 100
}