{
    "DateLastVerified": "2024-02-20T10:04:00Z",
    "ID": 223803,
    "UUID": "777925A8-9A86-4895-8D46-19870EFB3374",
    "DataProviderID": 2,
    "DataProvidersReference": "227277",
    "OperatorID": 5,
    "UsageTypeID": 1,
    "AddressInfo": {
        "ID": 224186,
        "Title": "SACRAMENTO 35TH AVE #1",
        "AddressLine1": "1395 35th Ave",
        "Town": "Sacramento",
        "StateOrProvince": "CA",
        "Postcode": "95822",
        "CountryID": 2,
        "Latitude": 38.52292,
        "Longitude": -121.5066,
        "ContactTelephone1": "888-758-4389",
        "AccessComments": "24 hours daily",
        "RelatedURL": "http://www.chargepoint.com/",
        "DistanceUnit": 0
    },
    "Connections": [
        {
            "ID": 374809,
            "ConnectionTypeID": 1,
            "LevelID": 2,
            "Amps": 16,
            "Voltage": 230,
            "PowerKW": 3.7,
            "CurrentTypeID": 10,
            "Quantity": 2,
            "Comments": "kW power is an estimate based on the connection type"
        }
    ],
    "StatusTypeID": 50,
    "DateLastStatusUpdate": "2024-02-20T10:04:00Z",
    "DateCreated": "2023-02-13T05:10:00Z",
    "SubmissionStatusTypeID": 100
}