{
    "DateLastVerified": "2023-07-12T09:15:00Z",
    "ID": 110951,
    "UUID": "4356CD60-AF40-43F3-A91C-4574D108AA9F",
    "DataProviderID": 2,
    "DataProvidersReference": "84532",
    "UsageTypeID": 5,
    "AddressInfo": {
        "ID": 111297,
        "Title": "Triovest",
        "AddressLine1": "80 Courtneypark Dr E",
        "Town": "Mississauga",
        "StateOrProvince": "ON",
        "Postcode": "L5T 2Y3",
        "CountryID": 44,
        "Latitude": 43.637139,
        "Longitude": -79.691526,
        "ContactTelephone1": "888-908-8303",
        "AccessComments": "24 hours daily; EV Route App\r\nPublic - Credit card at all times",
        "RelatedURL": "",
        "DistanceUnit": 0
    },
    "Connections": [
        {
            "ID": 156275,
            "ConnectionTypeID": 2,
            "LevelID": 3,
            "PowerKW": 50,
            "CurrentTypeID": 30,
            "Quantity": 1,
            "Comments": "kW power is an estimate based on the connection type"
        },
        {
            "ID": 156276,
            "ConnectionTypeID": 32,
            "LevelID": 3,
            "PowerKW": 50,
            "CurrentTypeID": 30,
            "Quantity": 1,
            "Comments": "kW power is an estimate based on the connection type"
        }
    ],
    "StatusTypeID": 50,
    "DateLastStatusUpdate": "2023-07-12T09:15:00Z",
    "DateCreated": "2018-10-18T23:36:00Z",
    "SubmissionStatusTypeID": 100
}