{
    "DateLastVerified": "2025-06-24T08:07:00Z",
    "ID": 232533,
    "UUID": "9C46BA74-B902-46E1-BCE1-1B34C54CA9F4",
    "DataProviderID": 2,
    "DataProvidersReference": "83210",
    "UsageTypeID": 2,
    "AddressInfo": {
        "ID": 232916,
        "Title": "Gouvernement Canada",
        "AddressLine1": "11 rue Laurier",
        "Town": "Gatineau",
        "StateOrProvince": "QC",
        "Postcode": "J8X 4A6",
        "CountryID": 44,
        "Latitude": 45.425395,
        "Longitude": -75.713094,
        "ContactTelephone1": "",
        "AccessComments": "",
        "RelatedURL": "",
        "DistanceUnit": 0
    },
    "Connections": [
        {
            "ID": 384380,
            "ConnectionTypeID": 1,
            "LevelID": 2,
            "Amps": 16,
            "Voltage": 230,
            "PowerKW": 3.7,
            "CurrentTypeID": 10,
            "Quantity": 2,
            "Comments": "kW power is an estimate based on the connection type"
        }
    ],
    "StatusTypeID": 50,
    "DateLastStatusUpdate": "2025-06-24T08:07:00Z",
    "DateCreated": "2023-02-13T05:34:00Z",
    "SubmissionStatusTypeID": 100
}