{
    "IsRecentlyVerified": true,
    "DateLastVerified": "2023-03-07T05:45:00Z",
    "ID": 247672,
    "UUID": "6A6909AC-F3B2-48B9-BE73-17395A5B3FCE",
    "DataProviderID": 2,
    "DataProvidersReference": "249731",
    "UsageTypeID": 2,
    "AddressInfo": {
        "ID": 248056,
        "Title": "Sparkle Solutions Corp.",
        "AddressLine1": "1560 Adelaide St N",
        "Town": "London",
        "StateOrProvince": "ON",
        "Postcode": "N5X 2C1",
        "CountryID": 44,
        "Latitude": 43.035933851011,
        "Longitude": -81.2538728460891,
        "ContactTelephone1": "",
        "AccessComments": "",
        "RelatedURL": "",
        "DistanceUnit": 0
    },
    "Connections": [
        {
            "ID": 414083,
            "ConnectionTypeID": 1,
            "LevelID": 2,
            "Amps": 16,
            "Voltage": 230,
            "PowerKW": 3.7,
            "CurrentTypeID": 10,
            "Quantity": 2
        }
    ],
    "GeneralComments": "Planned for future date. Not Operational.",
    "DatePlanned": "2023-06-15T00:00:00Z",
    "StatusTypeID": 150,
    "DateLastStatusUpdate": "2023-03-07T05:45:00Z",
    "DataQualityLevel": 3,
    "DateCreated": "2023-03-07T05:45:00Z",
    "SubmissionStatusTypeID": 100
}