{
    "DateLastVerified": "2018-10-11T13:44:00Z",
    "ID": 109139,
    "UUID": "62261C60-D3E1-4711-B21D-7D9912F26D5D",
    "DataProviderID": 1,
    "OperatorID": 23,
    "OperatorsReference": "45144",
    "UsageTypeID": 4,
    "AddressInfo": {
        "ID": 109485,
        "Title": "Solaz los Cabos",
        "AddressLine1": "Solaz los Cabos",
        "Postcode": "23405",
        "CountryID": 146,
        "Latitude": 22.973691,
        "Longitude": -109.781943,
        "ContactTelephone1": "+52 624 151 6022",
        "DistanceUnit": 0
    },
    "Connections": [
        {
            "ID": 154257,
            "ConnectionTypeID": 30,
            "StatusTypeID": 50,
            "LevelID": 2,
            "PowerKW": 13,
            "CurrentTypeID": 20,
            "Quantity": 1
        }
    ],
    "NumberOfPoints": 1,
    "GeneralComments": "1 Tesla Connector, up to 13kW.Available for customers. Please see front desk.",
    "StatusTypeID": 50,
    "DateLastStatusUpdate": "2018-10-11T13:44:00Z",
    "DateCreated": "2018-10-11T13:44:00Z",
    "SubmissionStatusTypeID": 200
}