{
    "DateLastVerified": "2020-10-24T19:50:00Z",
    "ID": 169586,
    "UUID": "3C4C40DD-4F8F-4CC4-A32A-2A62BB162D71",
    "DataProviderID": 1,
    "OperatorID": 3,
    "UsageTypeID": 4,
    "UsageCost": "Free, use Pod Point app or webpage charge.pod-point.com to confirm charge within 15mins",
    "AddressInfo": {
        "ID": 169945,
        "Title": "Aldi Menston",
        "AddressLine1": "Bradford Rd ",
        "AddressLine2": "",
        "Town": "Leeds",
        "StateOrProvince": "England",
        "Postcode": "LS20 8FA ",
        "CountryID": 1,
        "Latitude": 53.879212262088885,
        "Longitude": -1.725541836907496,
        "RelatedURL": "https://charge.pod-point.com/",
        "DistanceUnit": 0
    },
    "Connections": [
        {
            "ID": 258166,
            "ConnectionTypeID": 25,
            "StatusTypeID": 50,
            "LevelID": 2,
            "Amps": 32,
            "Voltage": 230,
            "PowerKW": 7,
            "CurrentTypeID": 10,
            "Quantity": 2
        },
        {
            "ID": 258167,
            "ConnectionTypeID": 25,
            "StatusTypeID": 50,
            "LevelID": 2,
            "PowerKW": 7,
            "CurrentTypeID": 10,
            "Quantity": 2
        }
    ],
    "NumberOfPoints": 1,
    "StatusTypeID": 50,
    "DateLastStatusUpdate": "2020-10-24T19:50:00Z",
    "DateCreated": "2020-10-24T19:50:00Z",
    "SubmissionStatusTypeID": 200
}