{
    "IsRecentlyVerified": false,
    "ID": 135938,
    "UUID": "E97F386D-71B6-4596-861B-442A95992479",
    "DataProviderID": 18,
    "DataProvidersReference": "bd315d3230d476a1aeb8f9087a78310f",
    "OperatorID": 2244,
    "UsageTypeID": 4,
    "AddressInfo": {
        "ID": 136284,
        "Title": "Rectory Road",
        "AddressLine1": "Rectory Road",
        "Town": "Barnes, London",
        "Postcode": "SW13 0BP",
        "CountryID": 1,
        "Latitude": 51.471647,
        "Longitude": -0.239442,
        "AccessComments": "",
        "RelatedURL": "https://www.ubitricity.com",
        "DistanceUnit": 0
    },
    "Connections": [
        {
            "ID": 190361,
            "ConnectionTypeID": 25,
            "Reference": "suby1100000494",
            "StatusTypeID": 50,
            "LevelID": 2,
            "Amps": 16,
            "Voltage": 230,
            "PowerKW": 3.7,
            "CurrentTypeID": 10
        }
    ],
    "StatusTypeID": 0,
    "DateLastStatusUpdate": "2021-04-25T05:46:00Z",
    "MetadataValues": [
        {
            "ID": 5790,
            "MetadataFieldID": 4,
            "ItemValue": "Contains public sector information licensed under the Open Government Licence v2.0. http://www.nationalarchives.gov.uk/doc/open-government-licence/version/2/"
        }
    ],
    "DataQualityLevel": 3,
    "DateCreated": "2019-12-24T05:22:00Z",
    "SubmissionStatusTypeID": 100
}