{
    "DateLastVerified": "2024-11-06T10:39:00Z",
    "ID": 18965,
    "UUID": "F2FB2E90-BFBC-42C7-9685-8F705AC87325",
    "DataProviderID": 1,
    "OperatorID": 22,
    "OperatorsReference": "SC151",
    "UsageTypeID": 4,
    "AddressInfo": {
        "ID": 19310,
        "Title": "Larne Leisure Centre",
        "AddressLine1": "28 Tower Rd",
        "Town": "Larne",
        "Postcode": "BT40 1AB",
        "CountryID": 1,
        "Latitude": 54.855201,
        "Longitude": -5.803055,
        "DistanceUnit": 0
    },
    "Connections": [
        {
            "ID": 91716,
            "ConnectionTypeID": 25,
            "Reference": "SC151",
            "StatusTypeID": 50,
            "LevelID": 2,
            "Amps": 32,
            "Voltage": 400,
            "PowerKW": 22,
            "CurrentTypeID": 20,
            "Quantity": 2
        }
    ],
    "NumberOfPoints": 2,
    "StatusTypeID": 100,
    "DateLastStatusUpdate": "2024-11-06T10:39:00Z",
    "DateCreated": "2013-09-05T03:51:00Z",
    "SubmissionStatusTypeID": 200
}