{
    "IsRecentlyVerified": true,
    "DateLastVerified": "2022-08-23T11:08:00Z",
    "ID": 200364,
    "UUID": "E9429514-0735-48F2-BEFB-C5D4EAE52D1F",
    "DataProviderID": 18,
    "DataProvidersReference": "245d395e27812854f7ba19a5bfea181c",
    "UsageTypeID": 4,
    "AddressInfo": {
        "ID": 200723,
        "Title": "Harbord Street",
        "AddressLine1": "Harbord Street",
        "Town": "Hammmersmith",
        "Postcode": "SW6 6PH",
        "CountryID": 1,
        "Latitude": 51.477776,
        "Longitude": -0.2173,
        "AccessComments": "",
        "RelatedURL": "https://www.fmconway.co.uk/home",
        "DistanceUnit": 0
    },
    "Connections": [
        {
            "ID": 334254,
            "ConnectionTypeID": 25,
            "Reference": "1",
            "StatusTypeID": 50,
            "LevelID": 2,
            "Amps": 16,
            "Voltage": 230,
            "PowerKW": 3.7,
            "CurrentTypeID": 10
        }
    ],
    "StatusTypeID": 0,
    "DateLastStatusUpdate": "2022-08-23T11:08:00Z",
    "MetadataValues": [
        {
            "ID": 20786,
            "MetadataFieldID": 4,
            "ItemValue": "Contains public sector information licensed under the Open Government Licence v2.0. http://www.nationalarchives.gov.uk/doc/open-government-licence/version/2/"
        }
    ],
    "DataQualityLevel": 3,
    "DateCreated": "2022-08-23T11:08:00Z",
    "SubmissionStatusTypeID": 100
}