{
    "DateLastVerified": "2025-07-03T07:21:00Z",
    "ID": 457660,
    "UUID": "188FF60B-7856-4534-BB4E-304C3B07017B",
    "DataProviderID": 39,
    "DataProvidersReference": "23031",
    "OperatorID": 3634,
    "UsageTypeID": 4,
    "AddressInfo": {
        "ID": 458049,
        "Title": "Аллея ТЦ",
        "AddressLine1": "ул. Григория Пономаренко, 41",
        "Town": "Краснодар",
        "Postcode": "350087",
        "CountryID": 185,
        "Latitude": 45.101911,
        "Longitude": 39.002322,
        "DistanceUnit": 0
    },
    "Connections": [
        {
            "ID": 769240,
            "ConnectionTypeID": 1040,
            "Reference": "2049",
            "StatusTypeID": 50,
            "LevelID": 3,
            "Amps": 250,
            "Voltage": 240,
            "PowerKW": 60,
            "CurrentTypeID": 30,
            "Quantity": 1
        },
        {
            "ID": 769241,
            "ConnectionTypeID": 33,
            "Reference": "2050",
            "StatusTypeID": 50,
            "LevelID": 3,
            "Amps": 200,
            "Voltage": 300,
            "PowerKW": 60,
            "CurrentTypeID": 30,
            "Quantity": 1
        }
    ],
    "StatusTypeID": 50,
    "DateLastStatusUpdate": "2025-07-03T07:21:00Z",
    "DateCreated": "2025-06-21T13:25:00Z",
    "SubmissionStatusTypeID": 200
}