{
    "DateLastVerified": "2024-11-02T18:23:00Z",
    "ID": 305819,
    "UUID": "7FDA8DF4-CFF0-4C8D-A5F1-BB792F7D5692",
    "DataProviderID": 1,
    "OperatorID": 207,
    "UsageTypeID": 4,
    "UsageCost": "0,59€/kWh DC - 0,39€/kWh AC ",
    "AddressInfo": {
        "ID": 306208,
        "Title": "Transgourmet GM Salamanca",
        "AddressLine1": "Calle Primera",
        "AddressLine2": "Polígono Industrial El Montalvo",
        "StateOrProvince": "Castilla y León",
        "Postcode": "37188",
        "CountryID": 210,
        "Latitude": 40.941792666515056,
        "Longitude": -5.652588324470457,
        "DistanceUnit": 0
    },
    "Connections": [
        {
            "ID": 578742,
            "ConnectionTypeID": 33,
            "StatusTypeID": 50,
            "LevelID": 3,
            "Amps": 200,
            "Voltage": 950,
            "PowerKW": 150,
            "CurrentTypeID": 30,
            "Quantity": 2,
            "Comments": "XCharge Juicepump150 DC charger allows charging one vehicle at 150kW, or two simultaneous charges at 75kW. Maximum amperage 200A (max power is limited to 80kW for 400V cars)"
        }
    ],
    "NumberOfPoints": 2,
    "StatusTypeID": 50,
    "DateLastStatusUpdate": "2024-11-02T18:23:00Z",
    "DateCreated": "2024-11-02T18:23:00Z",
    "SubmissionStatusTypeID": 200
}