{
    "MediaItems": [
        {
            "ID": 53064,
            "ChargePointID": 208496,
            "ItemURL": "https://media.openchargemap.io/images/ES/OCM208496/OCM-208496.orig.2025120820003733.jpg",
            "ItemThumbnailURL": "https://media.openchargemap.io/images/ES/OCM208496/OCM-208496.thmb.2025120820003733.jpg",
            "Comment": "",
            "IsEnabled": true,
            "IsVideo": false,
            "IsFeaturedItem": false,
            "IsExternalResource": false,
            "User": {
                "ID": 40036,
                "Username": "lm-ocm"
            },
            "DateCreated": "2025-12-08T20:01:00Z"
        }
    ],
    "DateLastVerified": "2025-12-08T20:01:00Z",
    "ID": 208496,
    "UUID": "E69F002D-A3F6-423E-A7DC-8A58CD8F4917",
    "DataProviderID": 1,
    "OperatorID": 3283,
    "UsageTypeID": 1,
    "UsageCost": "Free",
    "AddressInfo": {
        "ID": 208876,
        "Title": "Sa Cabaneta",
        "AddressLine1": "Carrer de la Casa del Poble",
        "Town": "Marratxí",
        "StateOrProvince": "Balearic Islands",
        "Postcode": "07141",
        "CountryID": 210,
        "Latitude": 39.622587024489235,
        "Longitude": 2.7416124261201276,
        "DistanceUnit": 0
    },
    "Connections": [
        {
            "ID": 346928,
            "ConnectionTypeID": 25,
            "StatusTypeID": 50,
            "LevelID": 2,
            "PowerKW": 7.4,
            "CurrentTypeID": 10,
            "Quantity": 1
        },
        {
            "ID": 346929,
            "ConnectionTypeID": 28,
            "StatusTypeID": 50,
            "LevelID": 1,
            "PowerKW": 2.3,
            "CurrentTypeID": 10,
            "Quantity": 1
        }
    ],
    "NumberOfPoints": 1,
    "StatusTypeID": 50,
    "DateLastStatusUpdate": "2025-12-08T20:01:00Z",
    "DateCreated": "2022-10-17T09:45:00Z",
    "SubmissionStatusTypeID": 200
}