{
    "DateLastVerified": "2022-09-04T10:05:00Z",
    "ID": 201596,
    "UUID": "E3AD15FB-CD61-4BBF-9049-B2A8B0D78FA4",
    "DataProviderID": 1,
    "OperatorID": 91,
    "UsageTypeID": 4,
    "AddressInfo": {
        "ID": 201960,
        "Title": "REPSOL Centrolid",
        "AddressLine1": "Avenida del Euro",
        "Town": "Valladolid",
        "StateOrProvince": "Castile and León",
        "Postcode": "47010",
        "CountryID": 210,
        "Latitude": 41.674643694140144,
        "Longitude": -4.718846748678288,
        "DistanceUnit": 0
    },
    "Connections": [
        {
            "ID": 336457,
            "ConnectionTypeID": 33,
            "StatusTypeID": 50,
            "LevelID": 2,
            "PowerKW": 50,
            "Quantity": 1
        },
        {
            "ID": 336458,
            "ConnectionTypeID": 2,
            "StatusTypeID": 50,
            "LevelID": 2,
            "PowerKW": 50,
            "Quantity": 1
        },
        {
            "ID": 336459,
            "ConnectionTypeID": 1036,
            "StatusTypeID": 50,
            "LevelID": 3,
            "PowerKW": 43,
            "CurrentTypeID": 20,
            "Quantity": 1
        }
    ],
    "NumberOfPoints": 1,
    "StatusTypeID": 50,
    "DateLastStatusUpdate": "2022-09-04T10:05:00Z",
    "DateCreated": "2022-09-03T13:04:00Z",
    "SubmissionStatusTypeID": 200
}