{
    "IsRecentlyVerified": true,
    "DateLastVerified": "2023-02-09T09:50:00Z",
    "ID": 216065,
    "UUID": "7760ABDB-1470-46D3-986F-4E37827B4658",
    "DataProviderID": 19,
    "DataProvidersReference": "12032",
    "AddressInfo": {
        "ID": 216445,
        "Title": "Recharge Punaisen Piipun Kievari",
        "AddressLine1": "Kauraleiväntie 10",
        "Town": "Nuutilanmäki",
        "StateOrProvince": "Etelä-Savo",
        "Postcode": "51760",
        "CountryID": 79,
        "Latitude": 61.769608,
        "Longitude": 27.5884603,
        "AccessComments": "",
        "DistanceUnit": 0
    },
    "Connections": [
        {
            "ID": 364384,
            "ConnectionTypeID": 2,
            "Reference": "1",
            "LevelID": 3,
            "Amps": 100,
            "Voltage": 500,
            "PowerKW": 50,
            "CurrentTypeID": 30,
            "Comments": "Mode 4"
        },
        {
            "ID": 364385,
            "ConnectionTypeID": 33,
            "Reference": "2",
            "Comments": "Mode 4"
        },
        {
            "ID": 364386,
            "ConnectionTypeID": 33,
            "Reference": "3",
            "Comments": "Mode 4"
        },
        {
            "ID": 364387,
            "ConnectionTypeID": 33,
            "Reference": "4",
            "Comments": "Mode 4"
        },
        {
            "ID": 364388,
            "ConnectionTypeID": 33,
            "Reference": "5",
            "Comments": "Mode 4"
        },
        {
            "ID": 364389,
            "ConnectionTypeID": 33,
            "Reference": "6",
            "Comments": "Mode 4"
        },
        {
            "ID": 364390,
            "ConnectionTypeID": 33,
            "Reference": "7",
            "Comments": "Mode 4"
        }
    ],
    "NumberOfPoints": 7,
    "StatusTypeID": 0,
    "DateLastStatusUpdate": "2023-02-09T09:50:00Z",
    "DataQualityLevel": 2,
    "DateCreated": "2023-02-09T09:50:00Z",
    "SubmissionStatusTypeID": 100
}