{
    "DateLastVerified": "2016-06-19T12:18:00Z",
    "ID": 68710,
    "UUID": "D0F5C84B-B40A-4460-8196-57372092D29A",
    "DataProviderID": 1,
    "OperatorID": 45,
    "UsageTypeID": 3,
    "AddressInfo": {
        "ID": 69056,
        "Title": "Störtebeker Festspiele",
        "AddressLine1": "Am Bodden 100",
        "Town": "Ralswiek",
        "StateOrProvince": "Bergen auf Rügen",
        "Postcode": "18528",
        "CountryID": 87,
        "Latitude": 54.47373,
        "Longitude": 13.44742999999994,
        "ContactTelephone1": "+493838/31100",
        "AccessComments": "Während der Festspiele 18.6. - 3.9. rund um die Uhr nutzbar, sonst nach telefonischer Anmeldung.\r\n",
        "DistanceUnit": 0
    },
    "Connections": [
        {
            "ID": 96365,
            "ConnectionTypeID": 29,
            "StatusTypeID": 50,
            "LevelID": 2,
            "Amps": 16,
            "Voltage": 230,
            "PowerKW": 3.7,
            "CurrentTypeID": 10,
            "Quantity": 1
        }
    ],
    "NumberOfPoints": 1,
    "StatusTypeID": 50,
    "DateLastStatusUpdate": "2016-06-19T12:18:00Z",
    "DateCreated": "2016-06-19T12:18:00Z",
    "SubmissionStatusTypeID": 200
}