{
    "DateLastVerified": "2021-07-12T02:52:00Z",
    "ID": 181015,
    "UUID": "7A0F56EE-6F8E-4510-BDF5-43524F5A4A38",
    "DataProviderID": 29,
    "DataProvidersReference": "16833",
    "OperatorID": 127,
    "AddressInfo": {
        "ID": 181374,
        "Title": "Stader Straße 67a",
        "AddressLine1": "Stader Straße 67a",
        "Town": "Otterndorf",
        "Postcode": "21762",
        "CountryID": 87,
        "Latitude": 53.809198,
        "Longitude": 8.911279,
        "DistanceUnit": 0
    },
    "Connections": [
        {
            "ID": 284804,
            "ConnectionTypeID": 25,
            "StatusTypeID": 50,
            "LevelID": 2,
            "PowerKW": 22,
            "CurrentTypeID": 20
        },
        {
            "ID": 284805,
            "ConnectionTypeID": 25,
            "StatusTypeID": 50,
            "LevelID": 2,
            "PowerKW": 22,
            "CurrentTypeID": 20
        }
    ],
    "StatusTypeID": 50,
    "DateLastStatusUpdate": "2021-07-12T02:52:00Z",
    "MetadataValues": [
        {
            "ID": 13309,
            "MetadataFieldID": 4,
            "ItemValue": "Data from the German chargepoint registry provided by Bundesnetzagentur.de under the CC-BY 4.0 license"
        }
    ],
    "DateCreated": "2021-07-08T10:01:00Z",
    "SubmissionStatusTypeID": 100
}