{
    "IsRecentlyVerified": true,
    "DateLastVerified": "2021-07-12T02:43:00Z",
    "ID": 185945,
    "UUID": "C5C9CC0C-E0F8-44AE-84F6-5146D5183ED3",
    "DataProviderID": 29,
    "DataProvidersReference": "12427",
    "AddressInfo": {
        "ID": 186304,
        "Title": "Ostdeutsche Straße (Parkplatz)",
        "AddressLine1": "Ostdeutsche Straße (Parkplatz)",
        "Town": "Alzey",
        "Postcode": "55232",
        "CountryID": 87,
        "Latitude": 49.747703,
        "Longitude": 8.114276,
        "DistanceUnit": 0
    },
    "Connections": [
        {
            "ID": 297276,
            "ConnectionTypeID": 25,
            "StatusTypeID": 50,
            "LevelID": 2,
            "PowerKW": 22,
            "CurrentTypeID": 20
        },
        {
            "ID": 297277,
            "ConnectionTypeID": 25,
            "StatusTypeID": 50,
            "LevelID": 2,
            "PowerKW": 22,
            "CurrentTypeID": 20
        }
    ],
    "StatusTypeID": 50,
    "DateLastStatusUpdate": "2021-07-12T02:43:00Z",
    "MetadataValues": [
        {
            "ID": 18187,
            "MetadataFieldID": 4,
            "ItemValue": "Data from the German chargepoint registry provided by Bundesnetzagentur.de under the CC-BY 4.0 license"
        }
    ],
    "DataQualityLevel": 3,
    "DateCreated": "2021-07-12T02:43:00Z",
    "SubmissionStatusTypeID": 100
}