{
    "IsRecentlyVerified": false,
    "DateLastVerified": "2015-10-26T09:09:00Z",
    "ID": 56265,
    "UUID": "2AB821F9-4396-4AE6-8D75-68DA92B1DBAD",
    "DataProviderID": 1,
    "OperatorID": 105,
    "UsageTypeID": 4,
    "AddressInfo": {
        "ID": 56611,
        "Title": "Stadtwerke Speyer",
        "AddressLine1": "Georg-Peter-Süß-Straße 2",
        "AddressLine2": "Germanshof",
        "Town": "Speyer",
        "StateOrProvince": "Speyer",
        "Postcode": "67346",
        "CountryID": 87,
        "Latitude": 49.30352,
        "Longitude": 8.448640000000069,
        "AccessComments": "Rund um die Uhr (24/7) nutzbar mit RWE Vertrag. Umgebung:Mitten im Gewerbegebiet\r\n",
        "DistanceUnit": 0
    },
    "Connections": [
        {
            "ID": 70947,
            "ConnectionTypeID": 25,
            "StatusTypeID": 50,
            "LevelID": 2,
            "Amps": 32,
            "Voltage": 400,
            "PowerKW": 22,
            "CurrentTypeID": 20,
            "Quantity": 2
        }
    ],
    "NumberOfPoints": 2,
    "StatusTypeID": 50,
    "DateLastStatusUpdate": "2015-10-26T09:09:00Z",
    "DataQualityLevel": 1,
    "DateCreated": "2015-10-26T09:09:00Z",
    "SubmissionStatusTypeID": 200
}