{
    "DateLastVerified": "2015-02-17T10:04:00Z",
    "ID": 41879,
    "UUID": "E4223448-AA82-44C7-8E05-4841A93657C8",
    "DataProviderID": 1,
    "OperatorID": 45,
    "UsageTypeID": 1,
    "UsageCost": "1€/h",
    "AddressInfo": {
        "ID": 42225,
        "Title": "Parkplatz Stadthafen",
        "AddressLine1": "Werderstraße 105",
        "Town": "Schwerin",
        "StateOrProvince": "Mecklenburg-Vorpommern",
        "Postcode": "19055",
        "CountryID": 87,
        "Latitude": 53.6297452847288,
        "Longitude": 11.4205943563417,
        "ContactTelephone1": "0385 3990-0",
        "ContactEmail": "info@nahverkehr-schwerin.de",
        "AccessComments": "2 kostenpflichtige immer nutzbare Parkplätze. Laden wird über Parkautomat nach Zeit (1€/h, max. 8€/Tag) bezahlt. Auch für Wohnmobile.",
        "RelatedURL": "http://www.nahverkehr-schwerin.de/parken/parken_stadthafen.html",
        "DistanceUnit": 0
    },
    "Connections": [
        {
            "ID": 50213,
            "ConnectionTypeID": 16,
            "StatusTypeID": 50,
            "LevelID": 2,
            "Amps": 16,
            "Voltage": 230,
            "PowerKW": 3.7,
            "CurrentTypeID": 10,
            "Quantity": 2
        },
        {
            "ID": 50214,
            "ConnectionTypeID": 28,
            "StatusTypeID": 50,
            "LevelID": 2,
            "Amps": 16,
            "Voltage": 230,
            "PowerKW": 3.7,
            "CurrentTypeID": 10,
            "Quantity": 2
        }
    ],
    "NumberOfPoints": 4,
    "StatusTypeID": 50,
    "DateLastStatusUpdate": "2015-02-17T10:04:00Z",
    "DateCreated": "2015-02-17T07:24:00Z",
    "SubmissionStatusTypeID": 200
}