{
    "IsRecentlyVerified": false,
    "DateLastVerified": "2019-06-26T05:36:00Z",
    "ID": 26018,
    "UUID": "3F001364-60FE-423B-8AD0-C44B187C6B79",
    "DataProviderID": 1,
    "OperatorID": 22,
    "OperatorsReference": "C4H6R",
    "AddressInfo": {
        "ID": 26364,
        "Title": "Greek Street",
        "AddressLine1": "Dublin 1",
        "Town": "Dublin",
        "CountryID": 3,
        "Latitude": 53.354892,
        "Longitude": -6.287405,
        "DistanceUnit": 0
    },
    "Connections": [
        {
            "ID": 28386,
            "ConnectionTypeID": 25,
            "StatusTypeID": 50,
            "LevelID": 2,
            "Amps": 32,
            "Voltage": 400,
            "PowerKW": 22,
            "CurrentTypeID": 20,
            "Quantity": 2
        }
    ],
    "NumberOfPoints": 2,
    "StatusTypeID": 50,
    "DateLastStatusUpdate": "2019-06-26T05:36:00Z",
    "DataQualityLevel": 2,
    "DateCreated": "2014-11-27T09:11:00Z",
    "SubmissionStatusTypeID": 100
}