{
    "DateLastVerified": "2013-06-29T08:51:00Z",
    "ID": 16928,
    "UUID": "068A49BE-38F5-47A5-96EA-5A3B49EF0F64",
    "DataProviderID": 22,
    "DataProvidersReference": "65F675B3CF48B79D1D4FE970F1688C6B",
    "AddressInfo": {
        "ID": 17273,
        "Title": "日産プリンス宮城販売中山店",
        "AddressLine1": "宮城県仙台市泉区南中山1-38-4",
        "CountryID": 114,
        "Latitude": 38.29785723,
        "Longitude": 140.8288818,
        "ContactTelephone1": "022-277-1990",
        "DistanceUnit": 0
    },
    "Connections": [
        {
            "ID": 17169,
            "ConnectionTypeID": 2,
            "LevelID": 2,
            "Amps": 100,
            "Voltage": 480,
            "PowerKW": 48,
            "Quantity": 1
        }
    ],
    "DateLastStatusUpdate": "2013-06-29T08:51:00Z",
    "DateCreated": "2013-06-29T08:51:00Z",
    "SubmissionStatusTypeID": 200
}