{
    "DateLastVerified": "2025-12-03T06:14:00Z",
    "ID": 462469,
    "UUID": "EFAA3C4A-6E83-46B7-8B36-EEAAD6806619",
    "DataProviderID": 43,
    "DataProvidersReference": "6F7E6EB1B1",
    "OperatorID": 3898,
    "UsageTypeID": 4,
    "AddressInfo": {
        "ID": 462858,
        "Title": "EV24 Charging Station,  6f",
        "AddressLine1": " 6f",
        "Town": "Kletno",
        "Postcode": "57-550",
        "CountryID": 179,
        "Latitude": 50.262543267519945,
        "Longitude": 16.87050996359832,
        "DistanceUnit": 0
    },
    "Connections": [
        {
            "ID": 777882,
            "ConnectionTypeID": 1036,
            "Reference": "PL-94597-1",
            "StatusTypeID": 50,
            "LevelID": 2,
            "Amps": 32,
            "Voltage": 400,
            "PowerKW": 22.2,
            "CurrentTypeID": 20,
            "Quantity": 1
        }
    ],
    "StatusTypeID": 50,
    "DateLastStatusUpdate": "2025-12-03T06:14:00Z",
    "DateCreated": "2025-10-27T03:45:00Z",
    "SubmissionStatusTypeID": 200
}