{
    "DateLastVerified": "2024-11-21T08:34:00Z",
    "ID": 306303,
    "UUID": "5541257F-1C55-4E49-BC64-B4BFFE94C691",
    "DataProviderID": 1,
    "OperatorID": 3802,
    "UsageTypeID": 4,
    "AddressInfo": {
        "ID": 306692,
        "Title": "City Center - Hurghada (-1)",
        "AddressLine1": "شارع البحر",
        "AddressLine2": "Arabia",
        "Town": "Hurghada",
        "StateOrProvince": "البحر الأحمر",
        "Postcode": "84935",
        "CountryID": 70,
        "Latitude": 27.256161872854577,
        "Longitude": 33.82897351765919,
        "DistanceUnit": 0
    },
    "Connections": [
        {
            "ID": 582029,
            "ConnectionTypeID": 25,
            "StatusTypeID": 50,
            "LevelID": 2,
            "PowerKW": 22,
            "CurrentTypeID": 20,
            "Quantity": 1
        }
    ],
    "NumberOfPoints": 1,
    "StatusTypeID": 50,
    "DateLastStatusUpdate": "2024-11-21T08:34:00Z",
    "DateCreated": "2024-11-21T08:34:00Z",
    "SubmissionStatusTypeID": 200
}