{
    "IsRecentlyVerified": false,
    "ID": 36117,
    "UUID": "7C0E5167-1D06-4085-B5C5-9AFAAA93FF74",
    "DataProviderID": 26,
    "DataProvidersReference": "22816",
    "OperatorID": 157,
    "OperatorsReference": "NewMotion 01000724",
    "UsageCost": "0.00 jaarabonnement",
    "AddressInfo": {
        "ID": 36463,
        "Title": "Leidsestraatweg 57",
        "AddressLine1": "Leidsestraatweg 57",
        "Town": "Den Haag",
        "Postcode": "2594 BB",
        "CountryID": 159,
        "Latitude": 52.0996017456055,
        "Longitude": 4.34862995147705,
        "ContactTelephone1": "088 0109500",
        "RelatedURL": "http://thenewmotion.nl/",
        "DistanceUnit": 0
    },
    "Connections": [
        {
            "ID": 39628,
            "ConnectionTypeID": 25,
            "LevelID": 2,
            "PowerKW": 3.7,
            "CurrentTypeID": 10
        },
        {
            "ID": 48240,
            "ConnectionTypeID": 25,
            "LevelID": 2,
            "PowerKW": 3.7,
            "CurrentTypeID": 10
        }
    ],
    "NumberOfPoints": 1,
    "StatusTypeID": 50,
    "DateLastStatusUpdate": "2016-06-04T02:50:00Z",
    "DataQualityLevel": 3,
    "DateCreated": "2015-01-09T06:05:00Z",
    "SubmissionStatusTypeID": 100
}