{
    "DateLastVerified": "2016-06-04T02:37:00Z",
    "ID": 68169,
    "UUID": "44A35EBC-3917-4834-ABDE-C39BF0EAB07E",
    "DataProviderID": 26,
    "DataProvidersReference": "93589",
    "OperatorID": 73,
    "OperatorsReference": "EV-Box EVB-P1536578",
    "UsageCost": "0.00 jaarabonnement",
    "AddressInfo": {
        "ID": 68515,
        "Title": "Hogehilweg 4",
        "AddressLine1": "Hogehilweg 4",
        "Town": "Amsterdam",
        "Postcode": "1101 CC",
        "CountryID": 159,
        "Latitude": 52.30781,
        "Longitude": 4.94633,
        "RelatedURL": "http://www.ev-box.nl",
        "DistanceUnit": 0
    },
    "Connections": [
        {
            "ID": 94983,
            "ConnectionTypeID": 25,
            "LevelID": 2,
            "PowerKW": 11,
            "CurrentTypeID": 10
        }
    ],
    "NumberOfPoints": 1,
    "StatusTypeID": 50,
    "DateLastStatusUpdate": "2016-06-04T02:37:00Z",
    "DateCreated": "2016-06-04T02:37:00Z",
    "SubmissionStatusTypeID": 100
}