{
    "DateLastVerified": "2020-08-27T05:13:00Z",
    "ID": 152807,
    "UUID": "3BBE2F9B-ACB8-46C6-B4BA-9C24FC144945",
    "DataProviderID": 28,
    "DataProvidersReference": "FR*S49*P49020*001",
    "UsageTypeID": 5,
    "AddressInfo": {
        "ID": 153160,
        "Title": "BEAUCOUZE - Parking Av De La Grange Aux Belles",
        "AddressLine1": "Parking Av De La Grange Aux Belles 49070 BEAUCOUZE",
        "CountryID": 80,
        "Latitude": 47.474972,
        "Longitude": -0.624794,
        "AccessComments": "24h/24 7j/7",
        "DistanceUnit": 0
    },
    "Connections": [
        {
            "ID": 214082,
            "ConnectionTypeID": 25,
            "StatusTypeID": 50,
            "LevelID": 2,
            "PowerKW": 18,
            "CurrentTypeID": 20
        },
        {
            "ID": 214083,
            "ConnectionTypeID": 28,
            "StatusTypeID": 50,
            "LevelID": 2,
            "PowerKW": 18,
            "CurrentTypeID": 10
        },
        {
            "ID": 247306,
            "ConnectionTypeID": 25,
            "StatusTypeID": 50,
            "LevelID": 2,
            "PowerKW": 18,
            "CurrentTypeID": 20
        },
        {
            "ID": 247307,
            "ConnectionTypeID": 28,
            "StatusTypeID": 50,
            "LevelID": 2,
            "PowerKW": 18,
            "CurrentTypeID": 10
        }
    ],
    "GeneralComments": "Recharge par badge et avec une application smartphone",
    "StatusTypeID": 50,
    "DateLastStatusUpdate": "2020-08-27T05:13:00Z",
    "DateCreated": "2020-03-15T10:54:00Z",
    "SubmissionStatusTypeID": 100
}