{
    "DateLastVerified": "2022-08-23T10:32:00Z",
    "ID": 197476,
    "UUID": "315B3C96-78F4-404C-9A31-CCD3A8B388D2",
    "DataProviderID": 28,
    "DataProvidersReference": "FR*AGX*P01143*C",
    "UsageTypeID": 5,
    "AddressInfo": {
        "ID": 197835,
        "Title": "DIVONNE LES BAINS - Esplanade du lac",
        "AddressLine1": "Esplanade du lac",
        "CountryID": 80,
        "Latitude": 46.35436111,
        "Longitude": 6.146527778,
        "AccessComments": "",
        "DistanceUnit": 0
    },
    "Connections": [
        {
            "ID": 329172,
            "ConnectionTypeID": 28,
            "StatusTypeID": 50,
            "LevelID": 2,
            "PowerKW": 22,
            "CurrentTypeID": 10
        },
        {
            "ID": 329173,
            "ConnectionTypeID": 1036,
            "StatusTypeID": 50,
            "LevelID": 2,
            "PowerKW": 22,
            "CurrentTypeID": 20
        }
    ],
    "GeneralComments": "Recharge par badge pour les abonnés, par carte bancaire, ou avec une application smartphone",
    "StatusTypeID": 50,
    "DateLastStatusUpdate": "2022-08-23T10:32:00Z",
    "DateCreated": "2022-08-23T10:32:00Z",
    "SubmissionStatusTypeID": 100
}