{
    "IsRecentlyVerified": false,
    "ID": 152268,
    "UUID": "E04CBDA2-6618-4FAB-845F-1F0482FF6439",
    "DataProviderID": 28,
    "DataProvidersReference": "FR*S86*PSORE*B046",
    "UsageTypeID": 5,
    "AddressInfo": {
        "ID": 152621,
        "Title": "B046",
        "AddressLine1": "Rue de la croix - 86330 - La Grimaudiere",
        "CountryID": 80,
        "Latitude": 46.80673,
        "Longitude": 0.01791,
        "AccessComments": "24/24 7/7 jours",
        "DistanceUnit": 0
    },
    "Connections": [
        {
            "ID": 213106,
            "ConnectionTypeID": 28,
            "StatusTypeID": 50,
            "LevelID": 2,
            "PowerKW": 18,
            "CurrentTypeID": 10
        },
        {
            "ID": 213107,
            "ConnectionTypeID": 25,
            "StatusTypeID": 50,
            "LevelID": 2,
            "PowerKW": 18,
            "CurrentTypeID": 20
        },
        {
            "ID": 245966,
            "ConnectionTypeID": 28,
            "StatusTypeID": 50,
            "LevelID": 2,
            "PowerKW": 18,
            "CurrentTypeID": 10
        },
        {
            "ID": 245967,
            "ConnectionTypeID": 25,
            "StatusTypeID": 50,
            "LevelID": 2,
            "PowerKW": 18,
            "CurrentTypeID": 20
        }
    ],
    "GeneralComments": "",
    "StatusTypeID": 50,
    "DateLastStatusUpdate": "2020-08-27T05:13:00Z",
    "DataQualityLevel": 2,
    "DateCreated": "2020-03-15T10:53:00Z",
    "SubmissionStatusTypeID": 100
}